geone/__init__.py
geone/_version.py
geone/blockdata.py
geone/covModel.py
geone/customcolors.py
geone/deesseinterface.py
geone/geosclassicinterface.py
geone/grf.py
geone/img.py
geone/imgplot.py
geone/imgplot3d.py
geone/markovChain.py
geone/multiGaussian.py
geone/pgs.py
geone/randProcess.py
geone/srf.py
geone/tools.py
geone/deesse_core/__init__.py
geone/deesse_core/_deesse.so
geone/deesse_core/deesse.py
geone/geosclassic_core/__init__.py
geone/geosclassic_core/_geosclassic.so
geone/geosclassic_core/geosclassic.py
geone-1.3.0.dist-info/licenses/LICENSE
geone-1.3.0.dist-info/METADATA
geone-1.3.0.dist-info/WHEEL
geone-1.3.0.dist-info/top_level.txt
geone-1.3.0.dist-info/RECORD
