Metadata-Version: 2.4
Name: geone
Version: 1.3.0
Summary: Geostatistics tools and Multiple Point Statistics
Author-email: Julien Straubhaar <julien.straubhaar@unine.ch>, Philippe Renard <philippe.renard@unine.ch>
License: 
Project-URL: Repository, https://github.com/randlab/geone
Project-URL: Issues, https://github.com/randlab/geone/issues
Keywords: Geostatistics,Multiple Point Statistics,deesse,two point statistics,covariance,variogram,simulation,kriging
Classifier: Programming Language :: Python :: 3
Requires-Python: >=3.9
License-File: LICENSE
Requires-Dist: matplotlib
Requires-Dist: numpy
Requires-Dist: pandas
Requires-Dist: pyvista
Requires-Dist: scipy
Dynamic: license
Dynamic: license-file
